[{
  "_id": {
    "$oid": "6821752fb56be4fbb48d0156"
  },
  "title": "Axios",
  "description": "Hace condultas.",
  "curso": {
    "$oid": "682171d3348bb42ff19c7849"
  },
  "comentarios": [],
  "creationdate": {
    "$date": "2025-05-12T04:12:31.758Z"
  },
  "__v": 0
},
{
  "_id": {
    "$oid": "68217588b56be4fbb48d0171"
  },
  "title": "Git",
  "description": "Es  bueno para trabajar en equipo",
  "curso": {
    "$oid": "682171d3348bb42ff19c7849"
  },
  "comentarios": [],
  "creationdate": {
    "$date": "2025-05-12T04:14:00.999Z"
  },
  "__v": 0
},
{
  "_id": {
    "$oid": "682175b9b56be4fbb48d017e"
  },
  "title": "Mongo DB",
  "description": "Es una base de datos no relacionesles.",
  "curso": {
    "$oid": "682171d3348bb42ff19c7843"
  },
  "comentarios": [],
  "creationdate": {
    "$date": "2025-05-12T04:14:49.826Z"
  },
  "__v": 0
},
{
  "_id": {
    "$oid": "6821762fb56be4fbb48d0181"
  },
  "title": "Hooks",
  "description": "Funciones que nos ayudan a manipular resultados del componente.",
  "curso": {
    "$oid": "682171d3348bb42ff19c7843"
  },
  "comentarios": [],
  "creationdate": {
    "$date": "2025-05-12T04:16:47.119Z"
  },
  "__v": 0
},
{
  "_id": {
    "$oid": "6821767fb56be4fbb48d0196"
  },
  "title": "Git status",
  "description": "Este comendo lista lo que subiremos a un repositorio.",
  "curso": {
    "$oid": "682171d3348bb42ff19c7846"
  },
  "comentarios": [],
  "creationdate": {
    "$date": "2025-05-12T04:18:07.655Z"
  },
  "__v": 0
},
{
  "_id": {
    "$oid": "682176f1b56be4fbb48d01db"
  },
  "title": "Sawgger",
  "description": "Nos ayuda hacer la documentacion de la rutas.",
  "curso": {
    "$oid": "682171d3348bb42ff19c7846"
  },
  "comentarios": [],
  "creationdate": {
    "$date": "2025-05-12T04:20:01.082Z"
  },
  "__v": 0
}]